aiohttp_things/__init__.py
aiohttp_things/py.typed
aiohttp_things/views.py
aiohttp_things/web_handlers.py
aiohttp_things-1.2.post0.dist-info/LICENSE
aiohttp_things-1.2.post0.dist-info/METADATA
aiohttp_things-1.2.post0.dist-info/WHEEL
aiohttp_things-1.2.post0.dist-info/RECORD
