Metadata-Version: 2.3
Name: aiohttp-things
Version: 1.2.post0
Summary: Modest utility collection for development with AIOHTTP framework.
License: MIT
Keywords: aiohttp,asyncio
Author: Ruslan Ilyasovich Gilfanov
Author-email: ri.gilfanov@yandex.ru>
Maintainer: Ruslan Ilyasovich Gilfanov
Maintainer-email: ri.gilfanov@yandex.ru>
Requires-Python: >=3.9,<3.15
Classifier: Development Status :: 5 - Production/Stable
Classifier: Framework :: aiohttp
Classifier: Framework :: AsyncIO
Classifier: License :: OSI Approved :: MIT License
Classifier: Operating System :: OS Independent
Classifier: Programming Language :: Python
Classifier: Programming Language :: Python :: 3
Classifier: Programming Language :: Python :: 3.9
Classifier: Programming Language :: Python :: 3.10
Classifier: Programming Language :: Python :: 3.11
Classifier: Programming Language :: Python :: 3.12
Classifier: Programming Language :: Python :: 3.13
Classifier: Programming Language :: Python :: 3.14
Classifier: Topic :: Internet
Classifier: Topic :: Internet :: WWW/HTTP
Classifier: Topic :: Software Development :: Libraries
Classifier: Topic :: Software Development :: Libraries :: Python Modules
Classifier: Typing :: Typed
Requires-Dist: aiohttp (>=3.13.3,<4)
